{"stats":{"minecraft:mined":{"minecraft:sweet_berry_bush":15,"minecraft:carrots":2},"minecraft:used":{"minecraft:sweet_berries":58,"minecraft:carrot":9},"minecraft:picked_up":{"minecraft:carrot":2,"minecraft:sweet_berries":336},"minecraft:custom":{"minecraft:talked_to_villager":2,"minecraft:time_since_rest":62978,"minecraft:walk_one_cm":46550,"minecraft:leave_game":3,"minecraft:play_time":62978,"minecraft:damage_dealt":30,"minecraft:jump":522,"minecraft:time_since_death":62978,"minecraft:sprint_one_cm":82726,"minecraft:fall_one_cm":11272,"minecraft:total_world_time":62978,"minecraft:fly_one_cm":89580,"minecraft:crouch_one_cm":2007,"minecraft:sneak_time":2021}},"DataVersion":4440}